MARtrix.py
MARtrix-0.0.2.dist-info/METADATA
MARtrix-0.0.2.dist-info/WHEEL
MARtrix-0.0.2.dist-info/top_level.txt
MARtrix-0.0.2.dist-info/RECORD
