Metadata-Version: 2.1
Name: MARtrix
Version: 0.0.2
Summary: Ripoff Numpy
Author: Ram
Keywords: python,matrices
Classifier: Development Status :: 3 - Alpha
Classifier: Intended Audience :: Education
Classifier: Programming Language :: Python :: 3
Classifier: Operating System :: MacOS :: MacOS X
Classifier: Operating System :: Microsoft :: Windows
